{"4xuPDFPrMfs9R6Bij1rt/w==":"sling%20logo%20updated%20(3)-128x128.png","qHQIxtnaG5ScCEXYdlt+ag==":"sling%20desktop%20wallpaper-2000x1125.jpg","ydT/qQ6kp7P2uzCrIoNL2Q==":"copy%20of%20slingtech-1400x1400.png","p/2kZEeOwQIXtjppbA8fHg==":"copy%20of%20slingtech-128x128.png","3lHEHUIVHCUwWyGSbfadXA==":"pexels-photo-2000x1333.png","GEi3TUkX3kLvmDCq6f+uQA==":"peter-hershey-2000x1333.jpg","kuI1bbbeLj+OYzCT6QO/pg==":"pexels-photo-2000x1334.png","ZJS+j9APj6P8oNHJjILdmA==":"divine_connections_website_screenshot_sling-1400x634.png","GX8KivcmebCiN5muwV7DSA==":"nopneu_screenshot_sling-1400x637.png","wFAnUO324St6/PEEJICqJA==":"copy%20of%20logos%20for%20robert%202%20(1)-1400x1400.png","+K8bqYpyFPcWH/wPNLFMTA==":"mbr-1400x933.jpg","ZRbGWRwp5tU314wsr5PngQ==":"sling_snippet-1400x2083.png","ytnvFurEG06CuxtFh54BTA==":"mbr-2000x1410.jpg","mAi0mnAWC+FmAHdsPGHe3Q==":"sling_snippet-2000x2976.png","Pw2Ey6wfVUL7yBQkci7JwA==":"mbr-2000x1333.jpg","sYk02L3OEpBkdnsdDJ7qIg==":"mbr-2000x2500.jpg","AJ7IBvuRc7qi16ZChYYHRA==":"mbr-2000x1200.jpg","kGHNMFfLYVHdOBpKC0y+Jg==":"mbr-2000x1322.jpg","f6q8DSSfTU2fkK1hgTsjkQ==":"mbr-2000x1500.jpg","0A8zp8LQuNMbI9iXPlU+AA==":"mbr-1-2000x1333.jpg","jo796MDK/SZmYRwr9O0xrg==":"mbr-2000x1027.jpg","39fR35/7Qg8etxFadN5Q4g==":"sling%20logo%20new%20phrase-1400x1400.png","R+wPoi5eb+f8xBY2wECCYA==":"sling%20logo%20new%20phrase-128x128.png","Np1kZx8IewBfMX1KRa7iMg==":"sling%20logo%20with%20phrase%203-1400x1400.png","gFrFaXhDauqFGqAo6fHTRQ==":"sling%20logo%20with%20phrase%203-128x128.png","6XEm3Blv6S6XzDnm5MElCg==":"how_to_hack_algebra_website_cover_photo-1400x559.png"}